ridge_map/__init__.py
ridge_map/ridge_map.py
ridge_map-0.0.6.dist-info/LICENSE
ridge_map-0.0.6.dist-info/METADATA
ridge_map-0.0.6.dist-info/WHEEL
ridge_map-0.0.6.dist-info/top_level.txt
ridge_map-0.0.6.dist-info/RECORD
