Metadata-Version: 2.2
Name: ridge_map
Version: 0.0.6
Summary: 1d lines, 3d maps
Home-page: https://github.com/ColCarroll/ridge_map
Author: Colin Carroll
Author-email: colcarroll@gmail.com
License: MIT
Classifier: Development Status :: 3 - Alpha
Classifier: Intended Audience :: Developers
Classifier: License :: OSI Approved :: MIT License
Classifier: Programming Language :: Python :: 3
Classifier: Programming Language :: Python :: 3.5
Classifier: Programming Language :: Python :: 3.6
Classifier: Programming Language :: Python :: 3.7
License-File: LICENSE
Requires-Dist: SRTM.py
Requires-Dist: numpy
Requires-Dist: matplotlib
Requires-Dist: scikit-image>=0.14.2
Dynamic: author
Dynamic: author-email
Dynamic: classifier
Dynamic: description
Dynamic: description-content-type
Dynamic: home-page
Dynamic: license
Dynamic: requires-dist
Dynamic: summary
